Overspeed/Const.py
Overspeed/Control.py
Overspeed/Function.py
Overspeed/Http.py
Overspeed/Journal.py
Overspeed/Library.py
Overspeed/Resource.py
Overspeed/Task.py
Overspeed/Websocket.py
Overspeed/__init__.py
overspeed-1.1.6.dist-info/licenses/LICENSE
overspeed-1.1.6.dist-info/METADATA
overspeed-1.1.6.dist-info/WHEEL
overspeed-1.1.6.dist-info/top_level.txt
overspeed-1.1.6.dist-info/RECORD
